

{
  "itemIdentifier": "cdif.bbr.metadata.ddiProperties.ddicdiValueDomain",
  "$schema": "metaschema.yaml",
  "name": "DDI-CDI Value Domain",
  "abstract": "DDI-CDI ValueDomain building block for CDIF metadata, covering both SubstantiveValueDomain (subject-matter values) and SentinelValueDomain (processing/missing-value codes). Inherits from ValueDomain. Defines properties: @type, @id, cdi:catalogDetails, cdi:displayLabel, cdi:identifier, cdi:recommendedDataType, cdi:isDescribedBy, cdi:takesValuesFrom, cdi:takesConceptsFrom, cdi:platformType (sentinel only).",
  "status": "under-development",
  "dateTimeAddition": "2026-03-29T00:00:00Z",
  "itemClass": "schema",
  "register": "cdif-building-block-register",
  "version": "0.1",
  "dateOfLastChange": "2026-03-30",
  "link": "https://github.com/usgin/metadataBuildingBlocks",
  "maturity": "draft",
  "scope": "unstable",
  "tags": [
    "CDIF",
    "DDI-CDI",
    "value domain",
    "representations",
    "variables",
    "sentinel",
    "missing values"
  ],
  "sources": [
    {
      "title": "DDI-CDI 1.0 Specification",
      "link": "https://ddialliance.org/Specification/DDI-CDI/1.0/"
    }
  ],
  "shaclShapes": {
    "cdif.bbr.metadata.ddiProperties.ddicdiValueDomain": [
      "https://cross-domain-interoperability-framework.github.io/metadataBuildingBlocks/_sources/ddiProperties/ddicdiValueDomain/rules.shacl"
    ]
  },
  "ldContext": "https://cross-domain-interoperability-framework.github.io/metadataBuildingBlocks/build/annotated/bbr/metadata/ddiProperties/ddicdiValueDomain/context.jsonld",
  "schema": {
    "application/yaml": "https://cross-domain-interoperability-framework.github.io/metadataBuildingBlocks/build/annotated/bbr/metadata/ddiProperties/ddicdiValueDomain/schema.yaml",
    "application/json": "https://cross-domain-interoperability-framework.github.io/metadataBuildingBlocks/build/annotated/bbr/metadata/ddiProperties/ddicdiValueDomain/schema.json"
  },
  "sourceSchema": "https://cross-domain-interoperability-framework.github.io/metadataBuildingBlocks/_sources/ddiProperties/ddicdiValueDomain/schema.yaml",
  "sourceLdContext": "https://cross-domain-interoperability-framework.github.io/metadataBuildingBlocks/_sources/ddiProperties/ddicdiValueDomain/context.jsonld",
  "resolvedSchemaProperties": "https://cross-domain-interoperability-framework.github.io/metadataBuildingBlocks/build/annotated/bbr/metadata/ddiProperties/ddicdiValueDomain/resolvedProperties.json",
  "sourceFiles": "https://cross-domain-interoperability-framework.github.io/metadataBuildingBlocks/_sources/ddiProperties/ddicdiValueDomain/",
  "rdfData": [],
  "validationPassed": false,
  "testOutputs": "https://github.com/Cross-Domain-Interoperability-Framework/metadataBuildingBlocks/blob/main/build/tests/bbr/metadata/ddiProperties/ddicdiValueDomain/",
  "examples": [
    {
      "title": "Example DDI-CDI value domains (substantive and sentinel).",
      "content": "Two value domains for a height variable: a SubstantiveValueDomain\nwith a described numeric domain (0-3 meters, Ratio level), and a\nSentinelValueDomain with missing value codes for the SAS platform.",
      "prefixes": {
        "cdi": "http://ddialliance.org/Specification/DDI-CDI/1.0/RDF/"
      },
      "snippets": [
        {
          "language": "json",
          "ref": "exampleDdicdiValueDomain.json",
          "code": "{\n    \"@context\": {\n        \"cdi\": \"http://ddialliance.org/Specification/DDI-CDI/1.0/RDF/\"\n    },\n    \"@graph\": [\n        {\n            \"@type\": [\"cdi:SubstantiveValueDomain\"],\n            \"@id\": \"urn:example:svd:height-meters\",\n            \"cdi:identifier\": {\n                \"@type\": [\"cdi:Identifier\"],\n                \"cdi:uri\": \"urn:example:svd:height-meters\"\n            },\n            \"cdi:displayLabel\": {\n                \"@type\": [\"cdi:LabelForDisplay\"],\n                \"cdi:languageSpecificString\": {\n                    \"@type\": [\"cdi:LanguageString\"],\n                    \"cdi:content\": \"Height in meters\",\n                    \"cdi:language\": \"en\"\n                }\n            },\n            \"cdi:recommendedDataType\": {\n                \"@type\": [\"cdi:ControlledVocabularyEntry\"],\n                \"cdi:entryValue\": \"xsd:decimal\",\n                \"cdi:vocabulary\": {\n                    \"@type\": [\"cdi:Reference\"],\n                    \"cdi:uri\": \"http://www.w3.org/2001/XMLSchema#\",\n                    \"cdi:description\": \"W3C XML Schema Definition Language datatypes\"\n                }\n            },\n            \"cdi:isDescribedBy\": {\n                \"@type\": [\"cdi:ValueAndConceptDescription\"],\n                \"@id\": \"urn:example:vcd:height-description\",\n                \"cdi:classificationLevel\": \"Ratio\",\n                \"cdi:description\": {\n                    \"@type\": [\"cdi:InternationalString\"],\n                    \"cdi:languageSpecificString\": {\n                        \"@type\": [\"cdi:LanguageString\"],\n                        \"cdi:content\": \"Real number between 0 and 3 representing height in meters\",\n                        \"cdi:language\": \"en\"\n                    }\n                },\n                \"cdi:minimumValueInclusive\": \"0\",\n                \"cdi:maximumValueInclusive\": \"3\"\n            }\n        },\n        {\n            \"@type\": [\"cdi:SentinelValueDomain\"],\n            \"@id\": \"urn:example:sentinel:height-missing-sas\",\n            \"cdi:identifier\": {\n                \"@type\": [\"cdi:Identifier\"],\n                \"cdi:uri\": \"urn:example:sentinel:height-missing-sas\"\n            },\n            \"cdi:displayLabel\": {\n                \"@type\": [\"cdi:LabelForDisplay\"],\n                \"cdi:languageSpecificString\": {\n                    \"@type\": [\"cdi:LanguageString\"],\n                    \"cdi:content\": \"Height missing value codes (SAS)\",\n                    \"cdi:language\": \"en\"\n                }\n            },\n            \"cdi:platformType\": {\n                \"@type\": [\"cdi:ControlledVocabularyEntry\"],\n                \"cdi:entryValue\": \"SASNumeric\",\n                \"cdi:name\": \"SAS Numeric Missing Values\",\n                \"cdi:vocabulary\": {\n                    \"@type\": [\"cdi:Reference\"],\n                    \"cdi:uri\": \"urn:ddi-cdi:cv:platformType\",\n                    \"cdi:description\": \"DDI-CDI platform type vocabulary\"\n                }\n            },\n            \"cdi:isDescribedBy\": {\n                \"@type\": [\"cdi:ValueAndConceptDescription\"],\n                \"@id\": \"urn:example:vcd:height-sentinel-description\",\n                \"cdi:classificationLevel\": \"Nominal\",\n                \"cdi:description\": {\n                    \"@type\": [\"cdi:InternationalString\"],\n                    \"cdi:languageSpecificString\": {\n                        \"@type\": [\"cdi:LanguageString\"],\n                        \"cdi:content\": \"SAS missing value codes: . (system missing), .R (refused), .N (not recorded)\",\n                        \"cdi:language\": \"en\"\n                    }\n                },\n                \"cdi:regularExpression\": {\n                    \"@type\": [\"cdi:TypedString\"],\n                    \"cdi:content\": \"^\\\\.[RN_]?$\",\n                    \"cdi:typeOfContent\": {\n                        \"@type\": [\"cdi:ControlledVocabularyEntry\"],\n                        \"cdi:entryValue\": \"PCRE\"\n                    }\n                }\n            },\n            \"cdi:takesConceptsFrom\": {\n                \"@id\": \"urn:example:sentinel-conceptual-domain:missing-reasons\"\n            }\n        }\n    ]\n}\n",
          "url": "https://cross-domain-interoperability-framework.github.io/metadataBuildingBlocks/build/tests/bbr/metadata/ddiProperties/ddicdiValueDomain/example_1_1.json"
        },
        {
          "language": "jsonld",
          "code": "{\n  \"@context\": [\n    {\n      \"cdi\": \"http://ddialliance.org/Specification/DDI-CDI/1.0/RDF/\"\n    },\n    \"https://cross-domain-interoperability-framework.github.io/metadataBuildingBlocks/build/annotated/bbr/metadata/ddiProperties/ddicdiValueDomain/context.jsonld\",\n    {\n      \"cdi\": \"http://ddialliance.org/Specification/DDI-CDI/1.0/RDF/\"\n    }\n  ],\n  \"@graph\": [\n    {\n      \"@type\": [\n        \"cdi:SubstantiveValueDomain\"\n      ],\n      \"@id\": \"urn:example:svd:height-meters\",\n      \"cdi:identifier\": {\n        \"@type\": [\n          \"cdi:Identifier\"\n        ],\n        \"cdi:uri\": \"urn:example:svd:height-meters\"\n      },\n      \"cdi:displayLabel\": {\n        \"@type\": [\n          \"cdi:LabelForDisplay\"\n        ],\n        \"cdi:languageSpecificString\": {\n          \"@type\": [\n            \"cdi:LanguageString\"\n          ],\n          \"cdi:content\": \"Height in meters\",\n          \"cdi:language\": \"en\"\n        }\n      },\n      \"cdi:recommendedDataType\": {\n        \"@type\": [\n          \"cdi:ControlledVocabularyEntry\"\n        ],\n        \"cdi:entryValue\": \"xsd:decimal\",\n        \"cdi:vocabulary\": {\n          \"@type\": [\n            \"cdi:Reference\"\n          ],\n          \"cdi:uri\": \"http://www.w3.org/2001/XMLSchema#\",\n          \"cdi:description\": \"W3C XML Schema Definition Language datatypes\"\n        }\n      },\n      \"cdi:isDescribedBy\": {\n        \"@type\": [\n          \"cdi:ValueAndConceptDescription\"\n        ],\n        \"@id\": \"urn:example:vcd:height-description\",\n        \"cdi:classificationLevel\": \"Ratio\",\n        \"cdi:description\": {\n          \"@type\": [\n            \"cdi:InternationalString\"\n          ],\n          \"cdi:languageSpecificString\": {\n            \"@type\": [\n              \"cdi:LanguageString\"\n            ],\n            \"cdi:content\": \"Real number between 0 and 3 representing height in meters\",\n            \"cdi:language\": \"en\"\n          }\n        },\n        \"cdi:minimumValueInclusive\": \"0\",\n        \"cdi:maximumValueInclusive\": \"3\"\n      }\n    },\n    {\n      \"@type\": [\n        \"cdi:SentinelValueDomain\"\n      ],\n      \"@id\": \"urn:example:sentinel:height-missing-sas\",\n      \"cdi:identifier\": {\n        \"@type\": [\n          \"cdi:Identifier\"\n        ],\n        \"cdi:uri\": \"urn:example:sentinel:height-missing-sas\"\n      },\n      \"cdi:displayLabel\": {\n        \"@type\": [\n          \"cdi:LabelForDisplay\"\n        ],\n        \"cdi:languageSpecificString\": {\n          \"@type\": [\n            \"cdi:LanguageString\"\n          ],\n          \"cdi:content\": \"Height missing value codes (SAS)\",\n          \"cdi:language\": \"en\"\n        }\n      },\n      \"cdi:platformType\": {\n        \"@type\": [\n          \"cdi:ControlledVocabularyEntry\"\n        ],\n        \"cdi:entryValue\": \"SASNumeric\",\n        \"cdi:name\": \"SAS Numeric Missing Values\",\n        \"cdi:vocabulary\": {\n          \"@type\": [\n            \"cdi:Reference\"\n          ],\n          \"cdi:uri\": \"urn:ddi-cdi:cv:platformType\",\n          \"cdi:description\": \"DDI-CDI platform type vocabulary\"\n        }\n      },\n      \"cdi:isDescribedBy\": {\n        \"@type\": [\n          \"cdi:ValueAndConceptDescription\"\n        ],\n        \"@id\": \"urn:example:vcd:height-sentinel-description\",\n        \"cdi:classificationLevel\": \"Nominal\",\n        \"cdi:description\": {\n          \"@type\": [\n            \"cdi:InternationalString\"\n          ],\n          \"cdi:languageSpecificString\": {\n            \"@type\": [\n              \"cdi:LanguageString\"\n            ],\n            \"cdi:content\": \"SAS missing value codes: . (system missing), .R (refused), .N (not recorded)\",\n            \"cdi:language\": \"en\"\n          }\n        },\n        \"cdi:regularExpression\": {\n          \"@type\": [\n            \"cdi:TypedString\"\n          ],\n          \"cdi:content\": \"^\\\\.[RN_]?$\",\n          \"cdi:typeOfContent\": {\n            \"@type\": [\n              \"cdi:ControlledVocabularyEntry\"\n            ],\n            \"cdi:entryValue\": \"PCRE\"\n          }\n        }\n      },\n      \"cdi:takesConceptsFrom\": {\n        \"@id\": \"urn:example:sentinel-conceptual-domain:missing-reasons\"\n      }\n    }\n  ]\n}",
          "url": "https://cross-domain-interoperability-framework.github.io/metadataBuildingBlocks/build/tests/bbr/metadata/ddiProperties/ddicdiValueDomain/example_1_1.jsonld"
        },
        {
          "language": "ttl",
          "code": "@prefix cdi: <http://ddialliance.org/Specification/DDI-CDI/1.0/RDF/> .\n\n<urn:example:sentinel:height-missing-sas> a cdi:SentinelValueDomain ;\n    cdi:displayLabel [ a cdi:LabelForDisplay ;\n            cdi:languageSpecificString [ a cdi:LanguageString ;\n                    cdi:content \"Height missing value codes (SAS)\" ;\n                    cdi:language \"en\" ] ] ;\n    cdi:identifier [ a cdi:Identifier ;\n            cdi:uri \"urn:example:sentinel:height-missing-sas\" ] ;\n    cdi:isDescribedBy <urn:example:vcd:height-sentinel-description> ;\n    cdi:platformType [ a cdi:ControlledVocabularyEntry ;\n            cdi:entryValue \"SASNumeric\" ;\n            cdi:name \"SAS Numeric Missing Values\" ;\n            cdi:vocabulary [ a cdi:Reference ;\n                    cdi:description \"DDI-CDI platform type vocabulary\" ;\n                    cdi:uri \"urn:ddi-cdi:cv:platformType\" ] ] ;\n    cdi:takesConceptsFrom <urn:example:sentinel-conceptual-domain:missing-reasons> .\n\n<urn:example:svd:height-meters> a cdi:SubstantiveValueDomain ;\n    cdi:displayLabel [ a cdi:LabelForDisplay ;\n            cdi:languageSpecificString [ a cdi:LanguageString ;\n                    cdi:content \"Height in meters\" ;\n                    cdi:language \"en\" ] ] ;\n    cdi:identifier [ a cdi:Identifier ;\n            cdi:uri \"urn:example:svd:height-meters\" ] ;\n    cdi:isDescribedBy <urn:example:vcd:height-description> ;\n    cdi:recommendedDataType [ a cdi:ControlledVocabularyEntry ;\n            cdi:entryValue \"xsd:decimal\" ;\n            cdi:vocabulary [ a cdi:Reference ;\n                    cdi:description \"W3C XML Schema Definition Language datatypes\" ;\n                    cdi:uri \"http://www.w3.org/2001/XMLSchema#\" ] ] .\n\n<urn:example:vcd:height-description> a cdi:ValueAndConceptDescription ;\n    cdi:classificationLevel \"Ratio\" ;\n    cdi:description [ a cdi:InternationalString ;\n            cdi:languageSpecificString [ a cdi:LanguageString ;\n                    cdi:content \"Real number between 0 and 3 representing height in meters\" ;\n                    cdi:language \"en\" ] ] ;\n    cdi:maximumValueInclusive \"3\" ;\n    cdi:minimumValueInclusive \"0\" .\n\n<urn:example:vcd:height-sentinel-description> a cdi:ValueAndConceptDescription ;\n    cdi:classificationLevel \"Nominal\" ;\n    cdi:description [ a cdi:InternationalString ;\n            cdi:languageSpecificString [ a cdi:LanguageString ;\n                    cdi:content \"SAS missing value codes: . (system missing), .R (refused), .N (not recorded)\" ;\n                    cdi:language \"en\" ] ] ;\n    cdi:regularExpression [ a cdi:TypedString ;\n            cdi:content \"^\\\\.[RN_]?$\" ;\n            cdi:typeOfContent [ a cdi:ControlledVocabularyEntry ;\n                    cdi:entryValue \"PCRE\" ] ] .\n\n",
          "url": "https://cross-domain-interoperability-framework.github.io/metadataBuildingBlocks/build/tests/bbr/metadata/ddiProperties/ddicdiValueDomain/example_1_1.ttl"
        }
      ]
    }
  ],
  "annotatedSchema": "$schema: https://json-schema.org/draft/2020-12/schema\ntitle: DDI-CDI Value Domain\ndescription: Unified DDI-CDI ValueDomain building block covering both SubstantiveValueDomain\n  (subject-matter values) and SentinelValueDomain (processing/missing-value codes).\n  Both inherit from ValueDomain. SentinelValueDomain adds an optional cdi:platformType\n  property. Supports described domains (ValueAndConceptDescription), enumerated domains\n  (EnumerationDomain), and conceptual domain references.\ntype: object\nproperties:\n  '@type':\n    description: Must include either cdi:SubstantiveValueDomain or cdi:SentinelValueDomain\n    type: array\n    items:\n      type: string\n    anyOf:\n    - contains:\n        const: cdi:SubstantiveValueDomain\n    - contains:\n        const: cdi:SentinelValueDomain\n    minItems: 1\n  '@id':\n    type: string\n    description: Identifier for this value domain node\n  cdi:catalogDetails:\n    description: Administrative catalog metadata for this value domain\n    $ref: '#/$defs/CatalogDetails'\n  cdi:displayLabel:\n    description: Multilingual display label\n    anyOf:\n    - $ref: '#/$defs/LabelForDisplay'\n    - type: array\n      items:\n        $ref: '#/$defs/LabelForDisplay'\n  cdi:identifier:\n    description: Formal identifier for this value domain\n    $ref: '#/$defs/Identifier'\n  cdi:recommendedDataType:\n    description: Recommended physical data type for values in this domain\n    $ref: '#/$defs/ControlledVocabularyEntry'\n  cdi:isDescribedBy:\n    description: Description of the value domain constraints (0..1). Inline ValueAndConceptDescription\n      or @id reference.\n    anyOf:\n    - $ref: '#/$defs/ValueAndConceptDescription'\n    - $ref: '#/$defs/id-reference'\n  cdi:takesValuesFrom:\n    description: Enumeration domain providing the set of permissible coded values\n      (0..1). Inline EnumerationDomain or @id reference.\n    anyOf:\n    - $ref: '#/$defs/EnumerationDomain'\n    - $ref: '#/$defs/id-reference'\n  cdi:takesConceptsFrom:\n    description: Reference to a conceptual domain (SubstantiveConceptualDomain or\n      SentinelConceptualDomain) that provides conceptual grounding for this value\n      domain (0..1). @id reference only.\n    $ref: '#/$defs/id-reference'\n  cdi:platformType:\n    description: '(SentinelValueDomain only) The type of software platform under which\n      sentinel codes will be used. Statistical software platforms use different sets\n      of codes to indicate missing values. Example values: SASNumeric, SPSSstyle,\n      Rstyle, StataNumeric, BlankString, EmptyString, Unrestricted.'\n    $ref: '#/$defs/ControlledVocabularyEntry'\nrequired:\n- '@type'\n$defs:\n  id-reference:\n    type: object\n    description: JSON-LD @id reference to a node defined elsewhere in the graph\n    properties:\n      '@id':\n        type: string\n        description: IRI or blank node identifier of the referenced node\n    required:\n    - '@id'\n  ObjectName:\n    type: object\n    description: DDI-CDI structured name wrapper (dt-ObjectName)\n    properties:\n      '@type':\n        type: array\n        items:\n          type: string\n        contains:\n          const: cdi:ObjectName\n        minItems: 1\n      cdi:name:\n        type: string\n        description: The name string\n      cdi:context:\n        description: Context or usage of this name\n        $ref: '#/$defs/ControlledVocabularyEntry'\n    required:\n    - cdi:name\n  LabelForDisplay:\n    type: object\n    description: DDI-CDI multilingual display label (dt-LabelForDisplay)\n    properties:\n      '@type':\n        type: array\n        items:\n          type: string\n        contains:\n          const: cdi:LabelForDisplay\n        minItems: 1\n      cdi:locationVariant:\n        description: Geographic or locale variant\n        $ref: '#/$defs/ControlledVocabularyEntry'\n      cdi:maxLength:\n        type: integer\n        description: Maximum display length\n      cdi:languageSpecificString:\n        description: The label text with language tag\n        $ref: '#/$defs/LanguageString'\n  LanguageString:\n    type: object\n    description: DDI-CDI language-tagged string (dt-LanguageString)\n    properties:\n      '@type':\n        type: array\n        items:\n          type: string\n        contains:\n          const: cdi:LanguageString\n        minItems: 1\n      cdi:content:\n        type: string\n        description: The text content\n      cdi:language:\n        type: string\n        description: ISO language code (e.g. en, fr, de)\n    required:\n    - cdi:content\n  InternationalString:\n    type: object\n    description: DDI-CDI multilingual string wrapper (dt-InternationalString)\n    properties:\n      '@type':\n        type: array\n        items:\n          type: string\n        contains:\n          const: cdi:InternationalString\n        minItems: 1\n      cdi:languageSpecificString:\n        description: Language-tagged string content\n        anyOf:\n        - $ref: '#/$defs/LanguageString'\n        - type: array\n          items:\n            $ref: '#/$defs/LanguageString'\n  Identifier:\n    type: object\n    description: DDI-CDI composite identifier (dt-Identifier)\n    properties:\n      '@type':\n        type: array\n        items:\n          type: string\n        contains:\n          const: cdi:Identifier\n        minItems: 1\n      cdi:ddiIdentifier:\n        description: DDI-specific IRDI identifier\n        $ref: '#/$defs/InternationalRegistrationDataIdentifier'\n      cdi:uri:\n        type: string\n        format: uri\n        description: URI form of the identifier\n      cdi:nonDdiIdentifier:\n        description: Non-DDI identifier\n        anyOf:\n        - $ref: '#/$defs/NonDdiIdentifier'\n        - type: array\n          items:\n            $ref: '#/$defs/NonDdiIdentifier'\n  InternationalRegistrationDataIdentifier:\n    type: object\n    description: DDI-CDI IRDI (dt-InternationalRegistrationDataIdentifier)\n    properties:\n      '@type':\n        type: array\n        items:\n          type: string\n        contains:\n          const: cdi:InternationalRegistrationDataIdentifier\n        minItems: 1\n      cdi:dataIdentifier:\n        type: string\n      cdi:registrationAuthorityIdentifier:\n        type: string\n      cdi:versionIdentifier:\n        type: string\n    required:\n    - cdi:dataIdentifier\n    - cdi:registrationAuthorityIdentifier\n    - cdi:versionIdentifier\n  NonDdiIdentifier:\n    type: object\n    description: Non-DDI identifier (dt-NonDdiIdentifier)\n    properties:\n      '@type':\n        type: array\n        items:\n          type: string\n        contains:\n          const: cdi:NonDdiIdentifier\n        minItems: 1\n      cdi:identifierContent:\n        type: string\n        description: The identifier value\n      cdi:managingAgency:\n        type: string\n        description: Agency managing this identifier scheme\n    required:\n    - cdi:identifierContent\n  Reference:\n    type: object\n    description: DDI-CDI reference to an entity (dt-Reference)\n    properties:\n      '@type':\n        type: array\n        items:\n          type: string\n        contains:\n          const: cdi:Reference\n        minItems: 1\n      cdi:uri:\n        type: string\n        format: uri\n        description: URI of the referenced entity\n      cdi:description:\n        type: string\n        description: Human-readable description of the reference\n      cdi:ddiReference:\n        description: DDI IRDI reference\n        $ref: '#/$defs/InternationalRegistrationDataIdentifier'\n      cdi:semantic:\n        description: Semantic role of this reference\n        $ref: '#/$defs/ControlledVocabularyEntry'\n  ControlledVocabularyEntry:\n    type: object\n    description: DDI-CDI controlled vocabulary entry (dt-ControlledVocabularyEntry)\n    properties:\n      '@type':\n        type: array\n        items:\n          type: string\n        contains:\n          const: cdi:ControlledVocabularyEntry\n        minItems: 1\n      cdi:entryValue:\n        type: string\n        description: The vocabulary code or value\n      cdi:name:\n        type: string\n        description: Human-readable name\n      cdi:vocabulary:\n        description: Reference to the vocabulary scheme\n        $ref: '#/$defs/Reference'\n  CatalogDetails:\n    type: object\n    description: DDI-CDI administrative catalog metadata (dt-CatalogDetails)\n    properties:\n      '@type':\n        type: array\n        items:\n          type: string\n        contains:\n          const: cdi:CatalogDetails\n        minItems: 1\n      cdi:title:\n        description: Title of the cataloged resource\n        $ref: '#/$defs/InternationalString'\n      cdi:summary:\n        description: Summary description\n        $ref: '#/$defs/InternationalString'\n      cdi:identifier:\n        description: Identifier for catalog entry\n        type: object\n        properties:\n          '@type':\n            type: array\n            items:\n              type: string\n            contains:\n              const: cdi:InternationalIdentifier\n            minItems: 1\n          cdi:identifierContent:\n            type: string\n            description: The identifier value\n          cdi:isUri:\n            type: boolean\n            description: Whether the identifier is a URI\n      cdi:creator:\n        description: Agent responsible for creation\n        $ref: '#/$defs/AgentInRole'\n  AgentInRole:\n    type: object\n    description: DDI-CDI agent with a role (cls-AgentInRole)\n    properties:\n      '@type':\n        type: array\n        items:\n          type: string\n        contains:\n          const: cdi:AgentInRole\n        minItems: 1\n      cdi:agentName:\n        description: Name of the agent\n        $ref: '#/$defs/InternationalString'\n      cdi:reference:\n        description: Reference to an external agent record\n        $ref: '#/$defs/Reference'\n      cdi:role:\n        description: Role of this agent\n        $ref: '#/$defs/ControlledVocabularyEntry'\n  ValueAndConceptDescription:\n    type: object\n    description: DDI-CDI description of value constraints and measurement level (cls-ValueAndConceptDescription)\n    properties:\n      '@type':\n        type: array\n        items:\n          type: string\n        contains:\n          const: cdi:ValueAndConceptDescription\n        minItems: 1\n      '@id':\n        type: string\n        description: Identifier for this description node\n      cdi:classificationLevel:\n        type: string\n        description: Level of measurement\n        enum:\n        - Continuous\n        - Interval\n        - Nominal\n        - Ordinal\n        - Ratio\n      cdi:description:\n        description: Textual description of the value domain constraints\n        $ref: '#/$defs/InternationalString'\n      cdi:formatPattern:\n        description: Expected format pattern for values\n        $ref: '#/$defs/ControlledVocabularyEntry'\n      cdi:identifier:\n        description: Formal identifier\n        $ref: '#/$defs/Identifier'\n      cdi:logicalExpression:\n        description: Logical expression constraining valid values\n        $ref: '#/$defs/ControlledVocabularyEntry'\n      cdi:maximumValueExclusive:\n        type: string\n        description: Exclusive upper bound for valid values\n      cdi:maximumValueInclusive:\n        type: string\n        description: Inclusive upper bound for valid values\n      cdi:minimumValueExclusive:\n        type: string\n        description: Exclusive lower bound for valid values\n      cdi:minimumValueInclusive:\n        type: string\n        description: Inclusive lower bound for valid values\n      cdi:regularExpression:\n        description: Regular expression constraining valid value syntax\n        $ref: '#/$defs/TypedString'\n  TypedString:\n    type: object\n    description: DDI-CDI typed string value (dt-TypedString)\n    properties:\n      '@type':\n        type: array\n        items:\n          type: string\n        contains:\n          const: cdi:TypedString\n        minItems: 1\n      cdi:content:\n        type: string\n        description: The string content\n      cdi:typeOfContent:\n        description: Type or format of the content\n        $ref: '#/$defs/ControlledVocabularyEntry'\n  EnumerationDomain:\n    type: object\n    description: DDI-CDI enumeration domain providing a set of permissible coded values\n      (cls-EnumerationDomain)\n    properties:\n      '@type':\n        type: array\n        items:\n          type: string\n        contains:\n          const: cdi:EnumerationDomain\n        minItems: 1\n      '@id':\n        type: string\n        description: Identifier for this enumeration domain node\n      cdi:identifier:\n        description: Formal identifier\n        $ref: '#/$defs/Identifier'\n      cdi:name:\n        description: Structured name for this enumeration domain\n        anyOf:\n        - $ref: '#/$defs/ObjectName'\n        - type: array\n          items:\n            $ref: '#/$defs/ObjectName'\n      cdi:purpose:\n        description: Purpose of this enumeration domain\n        $ref: '#/$defs/InternationalString'\n      cdi:uses:\n        description: Reference to a LevelStructure that organizes the enumeration.\n          @id reference only.\n        $ref: '#/$defs/id-reference'\n      cdi:isDefinedBy:\n        description: References to Concepts that define the enumerated values. Array\n          of @id references.\n        type: array\n        items:\n          $ref: '#/$defs/id-reference'\n      cdi:references:\n        description: Reference to the CategorySet providing the value categories.\n          @id reference only.\n        $ref: '#/$defs/id-reference'\nx-jsonld-prefixes:\n  cdi: http://ddialliance.org/Specification/DDI-CDI/1.0/RDF/\n",
  "gitRepository": "https://github.com/Cross-Domain-Interoperability-Framework/metadataBuildingBlocks",
  "gitPath": "_sources/ddiProperties/ddicdiValueDomain"
}