{
  "$schema": "https://json-schema.org/draft/2020-12/schema",
  "title": "DDI-CDI Individual",
  "description": "DDI-CDI Individual agent (cls-Individual, extends Agent). Represents a person with name, contact information, and identification.",
  "type": "object",
  "properties": {
    "@type": {
      "type": "array",
      "items": {
        "type": "string"
      },
      "contains": {
        "const": "cdi:Individual"
      },
      "minItems": 1
    },
    "@id": {
      "type": "string",
      "description": "Identifier for this individual node"
    },
    "cdi:individualName": {
      "description": "Name(s) of this individual",
      "anyOf": [
        {
          "type": "object",
          "description": "DDI-CDI individual name (dt-IndividualName)",
          "properties": {
            "@type": {
              "type": "array",
              "items": {
                "type": "string"
              },
              "contains": {
                "const": "cdi:IndividualName"
              },
              "minItems": 1
            },
            "cdi:firstGiven": {
              "type": "string",
              "description": "First or given name"
            },
            "cdi:lastFamily": {
              "type": "string",
              "description": "Last or family name"
            },
            "cdi:middle": {
              "type": "string",
              "description": "Middle name(s)"
            },
            "cdi:prefix": {
              "type": "string",
              "description": "Name prefix (e.g. Dr., Prof.)"
            },
            "cdi:suffix": {
              "type": "string",
              "description": "Name suffix (e.g. Jr., III)"
            },
            "cdi:fullName": {
              "$ref": "#/$defs/InternationalString",
              "description": "Full name as a single internationalized string"
            },
            "cdi:abbreviation": {
              "$ref": "#/$defs/InternationalString",
              "description": "Abbreviated form of the name"
            },
            "cdi:isFormal": {
              "type": "boolean",
              "default": true,
              "description": "Whether this is a formal name"
            },
            "cdi:isPreferred": {
              "type": "boolean",
              "default": false,
              "description": "Whether this is the preferred name"
            },
            "cdi:effectiveDates": {
              "$ref": "#/$defs/DateRange",
              "description": "Date range when this name is/was effective"
            },
            "cdi:context": {
              "$ref": "#/$defs/ControlledVocabularyEntry",
              "description": "Context or usage of this name"
            },
            "cdi:typeOfIndividualName": {
              "$ref": "#/$defs/ControlledVocabularyEntry",
              "description": "Classification of this name (e.g. birth, married, pen)"
            },
            "cdi:sex": {
              "type": "object",
              "description": "Sex specification associated with this name",
              "properties": {
                "@type": {
                  "type": "array",
                  "items": {
                    "type": "string"
                  },
                  "contains": {
                    "const": "cdi:SexSpecification"
                  },
                  "minItems": 1
                },
                "cdi:sexCode": {
                  "type": "string",
                  "description": "Code identifying sex (e.g. ISO 5218 values)"
                }
              }
            }
          }
        },
        {
          "type": "array",
          "items": {
            "type": "object",
            "description": "DDI-CDI individual name (dt-IndividualName)",
            "properties": {
              "@type": {
                "type": "array",
                "items": {
                  "type": "string"
                },
                "contains": {
                  "const": "cdi:IndividualName"
                },
                "minItems": 1
              },
              "cdi:firstGiven": {
                "type": "string",
                "description": "First or given name"
              },
              "cdi:lastFamily": {
                "type": "string",
                "description": "Last or family name"
              },
              "cdi:middle": {
                "type": "string",
                "description": "Middle name(s)"
              },
              "cdi:prefix": {
                "type": "string",
                "description": "Name prefix (e.g. Dr., Prof.)"
              },
              "cdi:suffix": {
                "type": "string",
                "description": "Name suffix (e.g. Jr., III)"
              },
              "cdi:fullName": {
                "$ref": "#/$defs/InternationalString",
                "description": "Full name as a single internationalized string"
              },
              "cdi:abbreviation": {
                "$ref": "#/$defs/InternationalString",
                "description": "Abbreviated form of the name"
              },
              "cdi:isFormal": {
                "type": "boolean",
                "default": true,
                "description": "Whether this is a formal name"
              },
              "cdi:isPreferred": {
                "type": "boolean",
                "default": false,
                "description": "Whether this is the preferred name"
              },
              "cdi:effectiveDates": {
                "$ref": "#/$defs/DateRange",
                "description": "Date range when this name is/was effective"
              },
              "cdi:context": {
                "$ref": "#/$defs/ControlledVocabularyEntry",
                "description": "Context or usage of this name"
              },
              "cdi:typeOfIndividualName": {
                "$ref": "#/$defs/ControlledVocabularyEntry",
                "description": "Classification of this name (e.g. birth, married, pen)"
              },
              "cdi:sex": {
                "type": "object",
                "description": "Sex specification associated with this name",
                "properties": {
                  "@type": {
                    "type": "array",
                    "items": {
                      "type": "string"
                    },
                    "contains": {
                      "const": "cdi:SexSpecification"
                    },
                    "minItems": 1
                  },
                  "cdi:sexCode": {
                    "type": "string",
                    "description": "Code identifying sex (e.g. ISO 5218 values)"
                  }
                }
              }
            }
          }
        }
      ]
    },
    "cdi:contactInformation": {
      "description": "Contact details for this individual",
      "anyOf": [
        {
          "type": "object",
          "description": "DDI-CDI contact information (dt-ContactInformation)",
          "properties": {
            "@type": {
              "type": "array",
              "items": {
                "type": "string"
              },
              "contains": {
                "const": "cdi:ContactInformation"
              },
              "minItems": 1
            },
            "cdi:address": {
              "description": "Postal address(es)",
              "anyOf": [
                {
                  "$ref": "#/$defs/Address"
                },
                {
                  "type": "array",
                  "items": {
                    "$ref": "#/$defs/Address"
                  }
                }
              ]
            },
            "cdi:email": {
              "description": "Email address(es)",
              "anyOf": [
                {
                  "$ref": "#/$defs/Email"
                },
                {
                  "type": "array",
                  "items": {
                    "$ref": "#/$defs/Email"
                  }
                }
              ]
            },
            "cdi:emessaging": {
              "description": "Electronic messaging contact(s)",
              "anyOf": [
                {
                  "$ref": "#/$defs/ElectronicMessageSystem"
                },
                {
                  "type": "array",
                  "items": {
                    "$ref": "#/$defs/ElectronicMessageSystem"
                  }
                }
              ]
            },
            "cdi:telephone": {
              "description": "Telephone number(s)",
              "anyOf": [
                {
                  "$ref": "#/$defs/Telephone"
                },
                {
                  "type": "array",
                  "items": {
                    "$ref": "#/$defs/Telephone"
                  }
                }
              ]
            },
            "cdi:website": {
              "description": "Website link(s)",
              "anyOf": [
                {
                  "$ref": "#/$defs/WebLink"
                },
                {
                  "type": "array",
                  "items": {
                    "$ref": "#/$defs/WebLink"
                  }
                }
              ]
            }
          }
        },
        {
          "type": "array",
          "items": {
            "type": "object",
            "description": "DDI-CDI contact information (dt-ContactInformation)",
            "properties": {
              "@type": {
                "type": "array",
                "items": {
                  "type": "string"
                },
                "contains": {
                  "const": "cdi:ContactInformation"
                },
                "minItems": 1
              },
              "cdi:address": {
                "description": "Postal address(es)",
                "anyOf": [
                  {
                    "$ref": "#/$defs/Address"
                  },
                  {
                    "type": "array",
                    "items": {
                      "$ref": "#/$defs/Address"
                    }
                  }
                ]
              },
              "cdi:email": {
                "description": "Email address(es)",
                "anyOf": [
                  {
                    "$ref": "#/$defs/Email"
                  },
                  {
                    "type": "array",
                    "items": {
                      "$ref": "#/$defs/Email"
                    }
                  }
                ]
              },
              "cdi:emessaging": {
                "description": "Electronic messaging contact(s)",
                "anyOf": [
                  {
                    "$ref": "#/$defs/ElectronicMessageSystem"
                  },
                  {
                    "type": "array",
                    "items": {
                      "$ref": "#/$defs/ElectronicMessageSystem"
                    }
                  }
                ]
              },
              "cdi:telephone": {
                "description": "Telephone number(s)",
                "anyOf": [
                  {
                    "$ref": "#/$defs/Telephone"
                  },
                  {
                    "type": "array",
                    "items": {
                      "$ref": "#/$defs/Telephone"
                    }
                  }
                ]
              },
              "cdi:website": {
                "description": "Website link(s)",
                "anyOf": [
                  {
                    "$ref": "#/$defs/WebLink"
                  },
                  {
                    "type": "array",
                    "items": {
                      "$ref": "#/$defs/WebLink"
                    }
                  }
                ]
              }
            }
          }
        }
      ]
    },
    "cdi:catalogDetails": {
      "type": "object",
      "description": "Catalog metadata for this agent",
      "properties": {
        "@type": {
          "type": "array",
          "items": {
            "type": "string"
          },
          "contains": {
            "const": "cdi:CatalogDetails"
          },
          "minItems": 1
        },
        "cdi:title": {
          "$ref": "#/$defs/InternationalString",
          "description": "Title for the catalog entry"
        },
        "cdi:summary": {
          "$ref": "#/$defs/InternationalString",
          "description": "Summary description"
        },
        "cdi:identifier": {
          "description": "Catalog identifier",
          "type": "object",
          "properties": {
            "cdi:identifierContent": {
              "type": "string"
            },
            "cdi:isUri": {
              "type": "boolean"
            }
          }
        },
        "cdi:creator": {
          "type": "object",
          "description": "Creator of the catalog entry",
          "properties": {
            "@type": {
              "type": "array",
              "items": {
                "type": "string"
              },
              "contains": {
                "const": "cdi:AgentInRole"
              },
              "minItems": 1
            },
            "cdi:agentName": {
              "$ref": "#/$defs/InternationalString",
              "description": "Name of the agent"
            },
            "cdi:reference": {
              "$ref": "#/$defs/Reference",
              "description": "Reference to the agent entity"
            },
            "cdi:role": {
              "$ref": "#/$defs/ControlledVocabularyEntry",
              "description": "Role of the agent"
            }
          }
        }
      }
    },
    "cdi:identifier": {
      "type": "object",
      "description": "Formal identifier for this agent",
      "properties": {
        "@type": {
          "type": "array",
          "items": {
            "type": "string"
          },
          "contains": {
            "const": "cdi:Identifier"
          },
          "minItems": 1
        },
        "cdi:ddiIdentifier": {
          "type": "object",
          "description": "DDI-specific IRDI identifier",
          "properties": {
            "@type": {
              "type": "array",
              "items": {
                "type": "string"
              },
              "contains": {
                "const": "cdi:InternationalRegistrationDataIdentifier"
              },
              "minItems": 1
            },
            "cdi:dataIdentifier": {
              "type": "string"
            },
            "cdi:registrationAuthorityIdentifier": {
              "type": "string"
            },
            "cdi:versionIdentifier": {
              "type": "string"
            }
          },
          "required": [
            "cdi:dataIdentifier",
            "cdi:registrationAuthorityIdentifier",
            "cdi:versionIdentifier"
          ]
        },
        "cdi:uri": {
          "type": "string",
          "format": "uri",
          "description": "URI form of the identifier"
        },
        "cdi:nonDdiIdentifier": {
          "description": "Non-DDI identifier",
          "anyOf": [
            {
              "type": "object",
              "description": "Non-DDI identifier (dt-NonDdiIdentifier)",
              "properties": {
                "@type": {
                  "type": "array",
                  "items": {
                    "type": "string"
                  },
                  "contains": {
                    "const": "cdi:NonDdiIdentifier"
                  },
                  "minItems": 1
                },
                "cdi:identifierContent": {
                  "type": "string",
                  "description": "The identifier value"
                },
                "cdi:managingAgency": {
                  "type": "string",
                  "description": "Agency managing this identifier scheme"
                }
              },
              "required": [
                "cdi:identifierContent"
              ]
            },
            {
              "type": "array",
              "items": {
                "type": "object",
                "description": "Non-DDI identifier (dt-NonDdiIdentifier)",
                "properties": {
                  "@type": {
                    "type": "array",
                    "items": {
                      "type": "string"
                    },
                    "contains": {
                      "const": "cdi:NonDdiIdentifier"
                    },
                    "minItems": 1
                  },
                  "cdi:identifierContent": {
                    "type": "string",
                    "description": "The identifier value"
                  },
                  "cdi:managingAgency": {
                    "type": "string",
                    "description": "Agency managing this identifier scheme"
                  }
                },
                "required": [
                  "cdi:identifierContent"
                ]
              }
            }
          ]
        }
      }
    },
    "cdi:image": {
      "type": "object",
      "description": "Image associated with this agent",
      "properties": {
        "@type": {
          "type": "array",
          "items": {
            "type": "string"
          },
          "contains": {
            "const": "cdi:PrivateImage"
          },
          "minItems": 1
        },
        "cdi:effectiveDates": {
          "$ref": "#/$defs/DateRange",
          "description": "Date range when this image is effective"
        },
        "cdi:privacy": {
          "$ref": "#/$defs/ControlledVocabularyEntry",
          "description": "Privacy classification"
        }
      }
    },
    "cdi:purpose": {
      "$ref": "#/$defs/InternationalString",
      "description": "Purpose or role of this agent"
    }
  },
  "required": [
    "@type"
  ],
  "$defs": {
    "InternationalString": {
      "type": "object",
      "description": "DDI-CDI internationalized string (dt-InternationalString)",
      "properties": {
        "@type": {
          "type": "array",
          "items": {
            "type": "string"
          },
          "contains": {
            "const": "cdi:InternationalString"
          },
          "minItems": 1
        },
        "cdi:languageSpecificString": {
          "description": "Language-tagged string value(s)",
          "anyOf": [
            {
              "type": "object",
              "description": "DDI-CDI language-tagged string (dt-LanguageString)",
              "properties": {
                "@type": {
                  "type": "array",
                  "items": {
                    "type": "string"
                  },
                  "contains": {
                    "const": "cdi:LanguageString"
                  },
                  "minItems": 1
                },
                "cdi:content": {
                  "type": "string",
                  "description": "The text content"
                },
                "cdi:language": {
                  "type": "string",
                  "description": "ISO language code (e.g. en, fr, de)"
                }
              },
              "required": [
                "cdi:content"
              ]
            },
            {
              "type": "array",
              "items": {
                "type": "object",
                "description": "DDI-CDI language-tagged string (dt-LanguageString)",
                "properties": {
                  "@type": {
                    "type": "array",
                    "items": {
                      "type": "string"
                    },
                    "contains": {
                      "const": "cdi:LanguageString"
                    },
                    "minItems": 1
                  },
                  "cdi:content": {
                    "type": "string",
                    "description": "The text content"
                  },
                  "cdi:language": {
                    "type": "string",
                    "description": "ISO language code (e.g. en, fr, de)"
                  }
                },
                "required": [
                  "cdi:content"
                ]
              }
            }
          ]
        }
      }
    },
    "DateRange": {
      "type": "object",
      "description": "DDI-CDI date range (dt-DateRange)",
      "properties": {
        "@type": {
          "type": "array",
          "items": {
            "type": "string"
          },
          "contains": {
            "const": "cdi:DateRange"
          },
          "minItems": 1
        },
        "cdi:startDate": {
          "type": "object",
          "description": "Start date of the range",
          "properties": {
            "@type": {
              "type": "array",
              "items": {
                "type": "string"
              },
              "contains": {
                "const": "cdi:CombinedDate"
              },
              "minItems": 1
            },
            "cdi:isoDate": {
              "type": "string",
              "format": "date-time",
              "description": "ISO 8601 date-time value"
            },
            "cdi:historicDate": {
              "type": "string",
              "description": "Free-text historic date"
            }
          }
        },
        "cdi:endDate": {
          "type": "object",
          "description": "End date of the range",
          "properties": {
            "@type": {
              "type": "array",
              "items": {
                "type": "string"
              },
              "contains": {
                "const": "cdi:CombinedDate"
              },
              "minItems": 1
            },
            "cdi:isoDate": {
              "type": "string",
              "format": "date-time",
              "description": "ISO 8601 date-time value"
            },
            "cdi:historicDate": {
              "type": "string",
              "description": "Free-text historic date"
            }
          }
        }
      }
    },
    "ControlledVocabularyEntry": {
      "type": "object",
      "description": "DDI-CDI controlled vocabulary entry (dt-ControlledVocabularyEntry). Allows for unstructured content which may be an entry from an externally maintained controlled vocabulary. When the content is from a controlled vocabulary, provide the code value of the entry along with a reference to the vocabulary from which the value is taken.",
      "properties": {
        "@type": {
          "type": "array",
          "items": {
            "type": "string"
          },
          "contains": {
            "const": "cdi:ControlledVocabularyEntry"
          },
          "minItems": 1
        },
        "cdi:entryReference": {
          "description": "A reference to the specific item in the vocabulary referenced by cdi:vocabulary, using a URI or other resolvable identifier.",
          "type": "array",
          "items": {
            "$ref": "#/$defs/Reference"
          },
          "minItems": 1
        },
        "cdi:entryValue": {
          "description": "The value of the entry of the controlled vocabulary. If no controlled vocabulary is used the term is entered here and none of the properties defining the controlled vocabulary location are used.",
          "type": "array",
          "items": {
            "type": "string"
          },
          "minItems": 1
        },
        "cdi:name": {
          "type": "string",
          "description": "The name of the code list (controlled vocabulary)."
        },
        "cdi:valueForOther": {
          "type": "string",
          "description": "If the value of the string is \"Other\" or the equivalent from the codelist, this attribute can provide a more specific value not found in the codelist."
        },
        "cdi:vocabulary": {
          "$ref": "#/$defs/Reference",
          "description": "A reference to the external controlled vocabulary, using a URI or other resolvable identifier."
        }
      }
    },
    "Address": {
      "type": "object",
      "description": "DDI-CDI postal address (dt-Address)",
      "properties": {
        "@type": {
          "type": "array",
          "items": {
            "type": "string"
          },
          "contains": {
            "const": "cdi:Address"
          },
          "minItems": 1
        },
        "cdi:line": {
          "description": "Address line(s)",
          "type": "array",
          "items": {
            "type": "string"
          }
        },
        "cdi:cityPlaceLocal": {
          "type": "string",
          "description": "City, town, or locality"
        },
        "cdi:stateProvince": {
          "type": "string",
          "description": "State, province, or region"
        },
        "cdi:postalCode": {
          "type": "string",
          "description": "Postal or ZIP code"
        },
        "cdi:countryCode": {
          "$ref": "#/$defs/ControlledVocabularyEntry",
          "description": "Country code"
        },
        "cdi:typeOfAddress": {
          "$ref": "#/$defs/ControlledVocabularyEntry",
          "description": "Type of address (e.g. home, work, mailing)"
        },
        "cdi:isPreferred": {
          "type": "boolean",
          "default": false,
          "description": "Whether this is the preferred address"
        }
      }
    },
    "Email": {
      "type": "object",
      "description": "DDI-CDI email address (dt-Email)",
      "properties": {
        "@type": {
          "type": "array",
          "items": {
            "type": "string"
          },
          "contains": {
            "const": "cdi:Email"
          },
          "minItems": 1
        },
        "cdi:internetEmail": {
          "type": "string",
          "description": "Email address string"
        },
        "cdi:typeOfEmail": {
          "$ref": "#/$defs/ControlledVocabularyEntry",
          "description": "Type of email (e.g. personal, work)"
        },
        "cdi:isPreferred": {
          "type": "boolean",
          "default": false,
          "description": "Whether this is the preferred email"
        }
      }
    },
    "ElectronicMessageSystem": {
      "type": "object",
      "description": "DDI-CDI electronic messaging system contact (dt-ElectronicMessageSystem)",
      "properties": {
        "@type": {
          "type": "array",
          "items": {
            "type": "string"
          },
          "contains": {
            "const": "cdi:ElectronicMessageSystem"
          },
          "minItems": 1
        },
        "cdi:contactAddress": {
          "type": "string",
          "description": "Messaging address or handle"
        },
        "cdi:typeOfService": {
          "$ref": "#/$defs/ControlledVocabularyEntry",
          "description": "Type of messaging service (e.g. Slack, Teams)"
        },
        "cdi:isPreferred": {
          "type": "boolean",
          "default": false,
          "description": "Whether this is the preferred messaging service"
        }
      }
    },
    "Telephone": {
      "type": "object",
      "description": "DDI-CDI telephone number (dt-Telephone)",
      "properties": {
        "@type": {
          "type": "array",
          "items": {
            "type": "string"
          },
          "contains": {
            "const": "cdi:Telephone"
          },
          "minItems": 1
        },
        "cdi:telephoneNumber": {
          "type": "string",
          "description": "Telephone number string"
        },
        "cdi:typeOfTelephone": {
          "$ref": "#/$defs/ControlledVocabularyEntry",
          "description": "Type of telephone (e.g. mobile, office, fax)"
        },
        "cdi:isPreferred": {
          "type": "boolean",
          "default": false,
          "description": "Whether this is the preferred telephone"
        }
      }
    },
    "WebLink": {
      "type": "object",
      "description": "DDI-CDI website link (dt-WebLink)",
      "properties": {
        "@type": {
          "type": "array",
          "items": {
            "type": "string"
          },
          "contains": {
            "const": "cdi:WebLink"
          },
          "minItems": 1
        },
        "cdi:uri": {
          "type": "string",
          "format": "uri",
          "description": "URI of the website"
        },
        "cdi:typeOfWebsite": {
          "$ref": "#/$defs/ControlledVocabularyEntry",
          "description": "Type of website (e.g. homepage, documentation)"
        },
        "cdi:isPreferred": {
          "type": "boolean",
          "default": false,
          "description": "Whether this is the preferred website"
        }
      }
    },
    "Reference": {
      "type": "object",
      "description": "DDI-CDI reference to an entity (dt-Reference)",
      "properties": {
        "@type": {
          "type": "array",
          "items": {
            "type": "string"
          },
          "contains": {
            "const": "cdi:Reference"
          },
          "minItems": 1
        },
        "cdi:uri": {
          "type": "string",
          "format": "uri",
          "description": "URI of the referenced entity"
        },
        "cdi:description": {
          "type": "string",
          "description": "Human-readable description of the reference"
        },
        "cdi:ddiReference": {
          "type": "object",
          "description": "DDI IRDI reference",
          "properties": {
            "@type": {
              "type": "array",
              "items": {
                "type": "string"
              },
              "contains": {
                "const": "cdi:InternationalRegistrationDataIdentifier"
              },
              "minItems": 1
            },
            "cdi:dataIdentifier": {
              "type": "string"
            },
            "cdi:registrationAuthorityIdentifier": {
              "type": "string"
            },
            "cdi:versionIdentifier": {
              "type": "string"
            }
          },
          "required": [
            "cdi:dataIdentifier",
            "cdi:registrationAuthorityIdentifier",
            "cdi:versionIdentifier"
          ]
        },
        "cdi:semantic": {
          "$ref": "#/$defs/ControlledVocabularyEntry",
          "description": "Semantic role of this reference"
        }
      }
    }
  }
}
